rosreestr2coord/__init__.py
rosreestr2coord/__main__.py
rosreestr2coord/batch.py
rosreestr2coord/console.py
rosreestr2coord/export.py
rosreestr2coord/logger.py
rosreestr2coord/parser.py
rosreestr2coord/utils.py
rosreestr2coord/request/__init__.py
rosreestr2coord/request/base_adapter.py
rosreestr2coord/request/exceptions.py
rosreestr2coord/request/helpers.py
rosreestr2coord/request/httpx_adapter.py
rosreestr2coord/request/proxy_handling.py
rosreestr2coord/request/request.py
rosreestr2coord/request/urlib_adapter.py
rosreestr2coord-5.3.1.dist-info/licenses/LICENSE.md
rosreestr2coord-5.3.1.dist-info/METADATA
rosreestr2coord-5.3.1.dist-info/WHEEL
rosreestr2coord-5.3.1.dist-info/entry_points.txt
rosreestr2coord-5.3.1.dist-info/top_level.txt
rosreestr2coord-5.3.1.dist-info/RECORD
