Metadata-Version: 2.4
Name: rosreestr2coord
Version: 5.3.1
Summary: Get geometry from rosreestr
Author-email: Artemiy Doroshkov <rendrom@gmail.com>
License: MIT License
Project-URL: Homepage, https://github.com/rendrom/rosreestr2coord
Classifier: Development Status :: 4 - Beta
Classifier: Programming Language :: Python :: 3
License-File: LICENSE.md
Requires-Dist: requests
Provides-Extra: dev
Requires-Dist: ruff; extra == "dev"
Requires-Dist: pytest; extra == "dev"
Requires-Dist: pytest-cov; extra == "dev"
Requires-Dist: pytest-mock; extra == "dev"
Requires-Dist: tox; extra == "dev"
Requires-Dist: requests-mock; extra == "dev"
Requires-Dist: build; extra == "dev"
Requires-Dist: twine; extra == "dev"
Dynamic: license-file
